econuy/__init__.py
econuy/base.py
econuy/load.py
econuy/retrieval/__init__.py
econuy/retrieval/activity.py
econuy/retrieval/datasets.json
econuy/retrieval/external.py
econuy/retrieval/financial.py
econuy/retrieval/fiscal.py
econuy/retrieval/global_.py
econuy/retrieval/income.py
econuy/retrieval/labor.py
econuy/retrieval/prices.py
econuy/retrieval/regional.py
econuy/transform/__init__.py
econuy/transform/change.py
econuy/transform/convert.py
econuy/transform/decompose.py
econuy/transform/rebase.py
econuy/transform/resample.py
econuy/transform/rolling.py
econuy/utils/__init__.py
econuy/utils/chromedriver.py
econuy/utils/exceptions.py
econuy/utils/extras.py
econuy/utils/operations.py
econuy/utils/retrieval.py
econuy/utils/transform.py
econuy/utils/x13.py
econuy/utils/files/bcra_certs.pem
econuy/utils/files/bcu_certs.pem
econuy/utils/files/inac_certs.pem
econuy/utils/files/ine_certs.pem
econuy-0.23.0.dist-info/LICENSE
econuy-0.23.0.dist-info/METADATA
econuy-0.23.0.dist-info/WHEEL
econuy-0.23.0.dist-info/top_level.txt
econuy-0.23.0.dist-info/RECORD
