Metadata-Version: 2.2
Name: econuy
Version: 0.23.0
Summary: Wrangling Uruguayan economic data so you don't have to.
Requires-Python: >=3.10
License-File: LICENSE
Requires-Dist: httpx>=0.28.1
Requires-Dist: lxml>=5.3.0
Requires-Dist: openpyxl>=3.1.5
Requires-Dist: opnieuw>=3.0.0
Requires-Dist: pandas>=2.2.3
Requires-Dist: patool>=3.1.0
Requires-Dist: python-dotenv>=1.0.1
Requires-Dist: selenium
Requires-Dist: statsmodels
Requires-Dist: tqdm>=4.67.1
Requires-Dist: xlrd>=2.0.1
